rbpe/__init__.py
rbpe/bpe_tokenizer_trainer.py
rbpe/cli.py
rbpe/data_cleaner.py
rbpe/dynamic_tokenizer.py
rbpe/logger_config.py
rbpe/mapping_tokenizer.py
rbpe/rbpe_tokenizer.py
rbpe/token_classifier.py
rbpe/data/arabic_chars_rbpe_norm.pickle
rbpe/data/unicode/Blocks.txt
rbpe/data/unicode/PropertyValueAliases.txt
rbpe/data/unicode/ScriptExtensions.txt
rbpe/data/unicode/Scripts.txt
rbpe/data/unicode_derived/alias_to_script_name.json
rbpe/data/unicode_derived/block_to_scripts.json
rbpe/data/unicode_derived/script_name_to_alias.json
rbpe/data/unicode_derived/script_to_blocks.json
rbpe/data/unicode_derived/unified_aliases.json
rbpe/utils/__init__.py
rbpe/utils/data_reader.py
rbpe/utils/generate_block_script_maps.py
rbpe/utils/unicode_normalizer.py
rbpe-0.1.1.dist-info/METADATA
rbpe-0.1.1.dist-info/WHEEL
rbpe-0.1.1.dist-info/entry_points.txt
rbpe-0.1.1.dist-info/RECORD
