Metadata-Version: 2.4
Name: rbpe
Version: 0.1.1
Summary: R-BPE: Improving BPE-Tokenizers with Token Reuse
Project-URL: Homepage, https://github.com/U4RASD/r-bpe
Project-URL: Repository, https://github.com/U4RASD/r-bpe
Project-URL: Issues, https://github.com/U4RASD/r-bpe/issues
Project-URL: Documentation, https://github.com/U4RASD/r-bpe#readme
Author-email: Nancy Hamdan <nhamdan@dohainstitute.edu.qa>, Osama Rakan Al Mraikhat <oalmraikhat@dohainstitute.edu.qa>, Digital Research Unit - Arab Center <dru@dohainstitute.edu.qa>
Maintainer-email: Nancy Hamdan <nhamdan@dohainstitute.edu.qa>, Osama Rakan Al Mraikhat <oalmraikhat@dohainstitute.edu.qa>, Digital Research Unit - Arab Center <dru@dohainstitute.edu.qa>
Keywords: arabic,bpe,bpe-tokenizer,large-language-models,low-resource-nlp,nlp,tokenizer,transformers,vocabulary-adaptation
Requires-Python: >=3.10.12
Requires-Dist: click>=7.0
Requires-Dist: datasets>=3.0.0
Requires-Dist: pytest>=7.0.0
Requires-Dist: torch>=2.4.0
Requires-Dist: tqdm>=4.60.0
Requires-Dist: transformers>=4.49.0
